aprilcmd/__init__.py
aprilcmd/acmd.py
aprilcmd/aload.py
aprilcmd/aprilcmd_config.json
aprilcmd/aunload.py
aprilcmd/data/__init__.py
aprilcmd/data/_base/__init__.py
aprilcmd/data/_base/root.host
aprilcmd/data/aarch64.repo
aprilcmd/data/default_file
aprilcmd/data/x86_64.repo
aprilcmd/items/__init__.py
aprilcmd/items/func/__init__.py
aprilcmd/items/func/base.py
aprilcmd/items/func/client.py
aprilcmd/items/func/ftp.py
aprilcmd/items/func/link.py
aprilcmd/items/func/nfs.py
aprilcmd/items/func/ssh.py
aprilcmd/items/func/web.py
aprilcmd/items/host/__init__.py
aprilcmd/items/host/host.py
aprilcmd/items/host/hostlist.py
aprilcmd/items/usb/__init__.py
aprilcmd/items/usb/ausb.py
aprilcmd/items/usb/usbbus.py
aprilcmd/main.py
aprilcmd/pcap.py
aprilcmd/root/__init__.py
aprilcmd/root/april/__init__.py
aprilcmd/root/april/april.py
aprilcmd/root/host/__init__.py
aprilcmd/root/host/host.py
aprilcmd/root/info/__init__.py
aprilcmd/root/info/info.py
aprilcmd/root/ksvd/__init__.py
aprilcmd/root/ksvd/client/__init__.py
aprilcmd/root/ksvd/client/client.py
aprilcmd/root/ksvd/ksvd.py
aprilcmd/root/ksvd/server/__init__.py
aprilcmd/root/ksvd/server/gluster/__init__.py
aprilcmd/root/ksvd/server/gluster/gluster.py
aprilcmd/root/ksvd/server/mpcd/__init__.py
aprilcmd/root/ksvd/server/mpcd/mpcd.py
aprilcmd/root/ksvd/server/node/__init__.py
aprilcmd/root/ksvd/server/node/node.py
aprilcmd/root/ksvd/server/policy/__init__.py
aprilcmd/root/ksvd/server/policy/policy.py
aprilcmd/root/ksvd/server/server.py
aprilcmd/root/ksvd/server/uniqbprod/__init__.py
aprilcmd/root/ksvd/server/uniqbprod/uniqbprod.py
aprilcmd/root/ksvd/server/user/__init__.py
aprilcmd/root/ksvd/server/user/user.py
aprilcmd/root/package/__init__.py
aprilcmd/root/package/item/__init__.py
aprilcmd/root/package/item/item.py
aprilcmd/root/package/module/__init__.py
aprilcmd/root/package/module/module.py
aprilcmd/root/package/package.py
aprilcmd/root/package/qemu/__init__.py
aprilcmd/root/package/qemu/qemu.py
aprilcmd/root/test/__init__.py
aprilcmd/third/tabulate-0.8.9.dist-info/INSTALLER
aprilcmd/third/tabulate-0.8.9.dist-info/LICENSE
aprilcmd/third/tabulate-0.8.9.dist-info/METADATA
aprilcmd/third/tabulate-0.8.9.dist-info/RECORD
aprilcmd/third/tabulate-0.8.9.dist-info/WHEEL
aprilcmd/third/tabulate-0.8.9.dist-info/entry_points.txt
aprilcmd/third/tabulate-0.8.9.dist-info/top_level.txt
aprilcmd-0.1.10.dist-info/METADATA
aprilcmd-0.1.10.dist-info/WHEEL
aprilcmd-0.1.10.dist-info/entry_points.txt
aprilcmd-0.1.10.dist-info/RECORD
