Metadata-Version: 2.1
Name: aprilcmd
Version: 0.1.10
Summary: aprilcmd
Author: youguanhua
Author-email: youguanhua@kylinos.com.cn
Requires-Python: >=3.10,<4.0
Classifier: Programming Language :: Python :: 3
Classifier: Programming Language :: Python :: 3.10
Classifier: Programming Language :: Python :: 3.11
Classifier: Programming Language :: Python :: 3.12
